TubeDL/__init__.py
TubeDL/tube.py
TubeDL_Land23-1.2.1.dist-info/LICENSE
TubeDL_Land23-1.2.1.dist-info/METADATA
TubeDL_Land23-1.2.1.dist-info/WHEEL
TubeDL_Land23-1.2.1.dist-info/entry_points.txt
TubeDL_Land23-1.2.1.dist-info/top_level.txt
TubeDL_Land23-1.2.1.dist-info/RECORD
