Metadata-Version: 2.1
Name: TubeDL-Land23
Version: 1.2.1
Summary: Command-line tool to download youtube videos
Home-page: https://github.com/LandStander27/TubeDL
Author: Land23
Author-email: landstander23@duck.com
License: UNKNOWN
Platform: UNKNOWN
Classifier: Programming Language :: Python :: 3
Classifier: License :: OSI Approved :: MIT License
Classifier: Operating System :: Microsoft :: Windows
Requires-Python: >=3.6
License-File: LICENSE
Requires-Dist: better-ffmpeg-progress (==2.0.2)
Requires-Dist: colorama (==0.4.4)
Requires-Dist: decorator (==5.1.0)
Requires-Dist: ffmpeg-python (==0.2.0)
Requires-Dist: future (==0.18.2)
Requires-Dist: pytube (==11.0.2)
Requires-Dist: six (==1.16.0)
Requires-Dist: tqdm (==4.62.3)
Requires-Dist: validators (==0.18.2)
Requires-Dist: setuptools (==59.2.0)
